setup.py
chunkify/__init__.py
chunkify/test_chunkify.py
chunkify.egg-info/PKG-INFO
chunkify.egg-info/SOURCES.txt
chunkify.egg-info/dependency_links.txt
chunkify.egg-info/pbr.json
chunkify.egg-info/top_level.txt