Metadata-Version: 1.0
Name: chunkify
Version: 1.2
Summary:  Python module to split an iterable into a certain number of chunks
Home-page: https://github.com/bhearsum/chunkify
Author: Ben Hearsum
Author-email: ben@hearsum.ca
License: MPL
Platform: UNKNOWN
